setup.py
django_logstream/__init__.py
django_logstream/utils.py
django_logstream.egg-info/PKG-INFO
django_logstream.egg-info/SOURCES.txt
django_logstream.egg-info/dependency_links.txt
django_logstream.egg-info/not-zip-safe
django_logstream.egg-info/requires.txt
django_logstream.egg-info/top_level.txt
django_logstream/client/__init__.py
django_logstream/client/models.py
django_logstream/client/views.py
django_logstream/client/handlers/__init__.py
django_logstream/client/handlers/common.py
django_logstream/client/handlers/threaded.py
django_logstream/server/__init__.py
django_logstream/server/models.py
django_logstream/server/storage.py
django_logstream/server/backends/__init__.py
django_logstream/server/backends/zeromq/__init__.py
django_logstream/server/backends/zeromq/base.py
django_logstream/server/management/__init__.py
django_logstream/server/management/commands/__init__.py
django_logstream/server/management/commands/logstreamd.py