Metadata-Version: 1.0
Name: django-logstream
Version: 1.1
Summary: Multiprocess log collector for python/django-logging
Home-page: https://github.com/niwibe/django-logstream
Author: Andrei Antoukh
Author-email: niwi@niwi.be
License: BSD
Platform: OS Independent
Classifier: Development Status :: 4 - Beta
Classifier: Framework :: Django
Classifier: Intended Audience :: Developers
Classifier: License :: OSI Approved :: BSD License
Classifier: Operating System :: OS Independent
Classifier: Programming Language :: Python
Classifier: Topic :: Internet :: WWW/HTTP
